[
  {
    "name": "Pitchoune",
    "sexe": "Femelle",
    "birthdate": "2019-10-01",
    "race": "Gouttière",
    "price": 1100.60,
    "comment": "Aime le calme du foyer, sort peu"
  },
  {
    "name": "Yamcha",
    "sexe": "Mâle",
    "birthdate": "2016-01-26",
    "race": "Balinois",
    "price": 800.00,
    "comment": "Jolie robe couleur sable,miaule beaucoup"
  },
  {
    "name": "Poukie",
    "sexe": "Femelle",
    "birthdate": "2015-09-16",
    "race": "Chartreux",
    "price": 150.60,
    "comment": "N'aime pas ses congénères"
  },
  {
    "name": "Plume",
    "sexe": "Femelle",
    "birthdate": "2019-10-01",
    "race": "Maine Coon",
    "price": 1500.00,
    "comment": "Espiègle et joueuse"
  },
  {
    "name": "Zizou",
    "sexe": "Mâle",
    "birthdate": "2019-01-30",
    "race": "Européen",
    "price": 10.00,
    "comment": "SOS animal malade"
  },
  {
    "name": "Séréna",
    "sexe": "Femelle",
    "birthdate": "2017-04-01",
    "race": "Ecaille de tortue",
    "price": 100.00,
    "comment": "chatte timide et réservée"
  },
  {
    "name": "Pitchin",
    "sexe": "Femelle",
    "birthdate": "2019-10-01",
    "race": "Gouttière",
    "price": 1100.60,
    "comment": "Aime le calme du foyer, sort peu"
  },
  {
    "name": "Yamchou",
    "sexe": "Mâle",
    "birthdate": "2016-01-26",
    "race": "Balinois",
    "price": 800.00,
    "comment": "Jolie robe couleur sable,miaule beaucoup"
  },
  {
    "name": "Poukette",
    "sexe": "Femelle",
    "birthdate": "2015-09-16",
    "race": "Chartreux",
    "price": 100.60,
    "comment": "N'aime pas ses congénères"
  },
  {
    "name": "Plumo",
    "sexe": "Mâle",
    "birthdate": "2018-10-01",
    "race": "Maine Coon",
    "price": 1500.25,
    "comment": "Espiègle et joueuse"
  },
  {
    "name": "Zilou",
    "sexe": "Mâle",
    "birthdate": "2019-11-30",
    "race": "Européen",
    "price": 10.00,
    "comment": "SOS animal malade"
  },
  {
    "name": "Vaiana",
    "sexe": "Femelle",
    "birthdate": "2017-04-01",
    "race": "Ecaille de tortue",
    "price": 100.00,
    "comment": "chatte timide et réservée"
  }
]